lightflask/__init__.py
lightflask/lightflask.py
lightflask-1.0.0.dist-info/LICENSE
lightflask-1.0.0.dist-info/METADATA
lightflask-1.0.0.dist-info/WHEEL
lightflask-1.0.0.dist-info/top_level.txt
lightflask-1.0.0.dist-info/RECORD
