Metadata-Version: 2.1
Name: lightflask
Version: 1.0.0
Summary: Lightweight Markdown Router for Flask
Home-page: https://github.com/eknvarli/lightflask
Author: Ekin Varli
Author-email: ekinnos@tutanota.com
Classifier: Programming Language :: Python :: 3
Classifier: License :: OSI Approved :: MIT License
Classifier: Operating System :: OS Independent
Requires-Python: >=3.9.8
License-File: LICENSE
Requires-Dist: Flask
Requires-Dist: markdown2
